addition.py
add_numbers_yourself-1.0.0.dist-info/METADATA
add_numbers_yourself-1.0.0.dist-info/WHEEL
add_numbers_yourself-1.0.0.dist-info/top_level.txt
add_numbers_yourself-1.0.0.dist-info/RECORD
