Metadata-Version: 2.1
Name: add-numbers-yourself
Version: 1.0.0
Summary: adding 2 numbers
Home-page: UNKNOWN
Author: anant shukla
Author-email: UNKNOWN
License: UNKNOWN
Keywords: adds numbers
Platform: UNKNOWN
